apifrom/__init__.py
apifrom/config.py
apifrom/health.py
apifrom/logging.py
apifrom/logging_utils.py
apifrom/main.py
apifrom/monitoring.py
apifrom/adapters/__init__.py
apifrom/adapters/aws_lambda.py
apifrom/adapters/azure_functions.py
apifrom/adapters/gcp_functions.py
apifrom/adapters/netlify.py
apifrom/adapters/vercel.py
apifrom/core/__init__.py
apifrom/core/app.py
apifrom/core/request.py
apifrom/core/response.py
apifrom/core/router.py
apifrom/decorators/__init__.py
apifrom/decorators/api.py
apifrom/decorators/web.py
apifrom/decorators/web_optimize.py
apifrom/docs/__init__.py
apifrom/docs/openapi.py
apifrom/docs/swagger_ui.py
apifrom/docs/templates/themes/flattop.css
apifrom/docs/templates/themes/material.css
apifrom/docs/templates/themes/muted.css
apifrom/docs/templates/themes/outline.css
apifrom/middleware/__init__.py
apifrom/middleware/base.py
apifrom/middleware/cache.py
apifrom/middleware/cache_advanced.py
apifrom/middleware/cors.py
apifrom/middleware/error_handling.py
apifrom/middleware/rate_limit.py
apifrom/monitoring/__init__.py
apifrom/monitoring/exporters.py
apifrom/monitoring/metrics.py
apifrom/monitoring/middleware.py
apifrom/performance/__init__.py
apifrom/performance/batch_processing.py
apifrom/performance/cache_optimizer.py
apifrom/performance/connection_pool.py
apifrom/performance/optimization.py
apifrom/performance/profiler.py
apifrom/performance/request_coalescing.py
apifrom/plugins/__init__.py
apifrom/plugins/base.py
apifrom/plugins/logging.py
apifrom/security/__init__.py
apifrom/security/auth.py
apifrom/security/cors.py
apifrom/security/csp.py
apifrom/security/csrf.py
apifrom/security/headers.py
apifrom/security/hsts.py
apifrom/security/permissions_policy.py
apifrom/security/sri.py
apifrom/security/trusted_types.py
apifrom/utils/__init__.py
apifrom/utils/cache_advanced.py
apifrom/utils/cors.py
apifrom/utils/csrf.py
apifrom/utils/hsts.py
apifrom/utils/permissions_policy.py
apifrom/utils/rate_limit.py
apifrom/utils/security_headers.py
apifrom-1.0.0.dist-info/LICENSE
apifrom-1.0.0.dist-info/METADATA
apifrom-1.0.0.dist-info/WHEEL
apifrom-1.0.0.dist-info/top_level.txt
apifrom-1.0.0.dist-info/RECORD
