Metadata-Version: 2.2
Name: apifrom
Version: 1.0.0
Summary: Transform any Python function into a REST API endpoint
Home-page: https://github.com/yourusername/apifrom
Author: Your Name
Author-email: sc4rfurry <akalucifr@protonmail.ch>
License: MIT
Project-URL: Homepage, https://github.com/sc4rfurry/apifrom
Project-URL: Bug Tracker, https://github.com/sc4rfurry/apifrom/issues
Project-URL: Documentation, https://github.com/sc4rfurry/apifrom/blob/main/README.md
Project-URL: Source Code, https://github.com/sc4rfurry/apifrom
Keywords: api,rest,web,async,framework
Classifier: Development Status :: 5 - Production/Stable
Classifier: Intended Audience :: Developers
Classifier: License :: OSI Approved :: MIT License
Classifier: Programming Language :: Python :: 3
Classifier: Programming Language :: Python :: 3.7
Classifier: Programming Language :: Python :: 3.8
Classifier: Programming Language :: Python :: 3.9
Classifier: Programming Language :: Python :: 3.10
Classifier: Topic :: Internet :: WWW/HTTP
Classifier: Topic :: Software Development :: Libraries :: Application Frameworks
Requires-Python: >=3.8
License-File: LICENSE
Requires-Dist: starlette>=0.20.0
Requires-Dist: pydantic>=1.8.0
Requires-Dist: uvicorn>=0.17.0
Requires-Dist: typing-extensions>=4.0.0
Requires-Dist: python-multipart>=0.0.5
Requires-Dist: jinja2>=3.0.0
Requires-Dist: httpx>=0.22.0
Requires-Dist: pyjwt>=2.4.0
Requires-Dist: cryptography>=37.0.0
Requires-Dist: passlib>=1.7.4
Provides-Extra: database
Requires-Dist: sqlalchemy>=1.4.0; extra == "database"
Requires-Dist: asyncpg>=0.25.0; extra == "database"
Requires-Dist: aiomysql>=0.1.0; extra == "database"
Requires-Dist: aiosqlite>=0.17.0; extra == "database"
Provides-Extra: cache
Requires-Dist: redis>=4.3.0; extra == "cache"
Requires-Dist: aioredis>=2.0.0; extra == "cache"
Provides-Extra: monitoring
Requires-Dist: prometheus-client>=0.14.0; extra == "monitoring"
Provides-Extra: dev
Requires-Dist: pytest>=7.1.0; extra == "dev"
Requires-Dist: pytest-asyncio>=0.18.0; extra == "dev"
Requires-Dist: pytest-cov>=3.0.0; extra == "dev"
Requires-Dist: black>=22.3.0; extra == "dev"
Requires-Dist: isort>=5.10.0; extra == "dev"
Requires-Dist: mypy>=0.950; extra == "dev"
Requires-Dist: flake8>=4.0.0; extra == "dev"
Provides-Extra: all
Requires-Dist: sqlalchemy>=1.4.0; extra == "all"
Requires-Dist: asyncpg>=0.25.0; extra == "all"
Requires-Dist: aiomysql>=0.1.0; extra == "all"
Requires-Dist: aiosqlite>=0.17.0; extra == "all"
Requires-Dist: redis>=4.3.0; extra == "all"
Requires-Dist: aioredis>=2.0.0; extra == "all"
Requires-Dist: prometheus-client>=0.14.0; extra == "all"
Dynamic: author
Dynamic: home-page
Dynamic: requires-python
